pyneuralfx/__init__.py
pyneuralfx/eval_metrics/eval_metrics.py
pyneuralfx/eval_metrics/utils.py
pyneuralfx/loss_func/loss_func.py
pyneuralfx/loss_func/utils.py
pyneuralfx/models/base.py
pyneuralfx/models/cnn/basic_block.py
pyneuralfx/models/cnn/blocks.py
pyneuralfx/models/cnn/gcn.py
pyneuralfx/models/cnn/tcn.py
pyneuralfx/models/filters/analog_filters.py
pyneuralfx/models/rnn/base.py
pyneuralfx/models/rnn/cells.py
pyneuralfx/models/rnn/constants.py
pyneuralfx/models/rnn/gru.py
pyneuralfx/models/rnn/lstm.py
pyneuralfx/models/rnn/rnn.py
pyneuralfx/models/utils.py
pyneuralfx/pyneuralfx.py
pyneuralfx/transient_sep/sms_tools/__init__.py
pyneuralfx/transient_sep/sms_tools/dftModel.py
pyneuralfx/transient_sep/sms_tools/sineModel.py
pyneuralfx/transient_sep/sms_tools/stochasticModel.py
pyneuralfx/transient_sep/sms_tools/utilFunctions.py
pyneuralfx/transient_sep/stn.py
pyneuralfx/transient_sep/tms_tools.py
pyneuralfx/transient_sep/utils.py
pyneuralfx/vis/plotting.py
pyneuralfx/vis/sysplotting.py
pyneuralfx/vis/utils.py
pyneuralfx-0.1.2.dist-info/LICENSE
pyneuralfx-0.1.2.dist-info/METADATA
pyneuralfx-0.1.2.dist-info/WHEEL
pyneuralfx-0.1.2.dist-info/RECORD
