Metadata-Version: 2.1
Name: pyneuralfx
Version: 0.1.2
Summary: A python package for neural audio effect
License: MIT
Author: yytung
Requires-Python: >=3.9,<4.0
Classifier: License :: OSI Approved :: MIT License
Classifier: Programming Language :: Python :: 3
Classifier: Programming Language :: Python :: 3.9
Classifier: Programming Language :: Python :: 3.10
Classifier: Programming Language :: Python :: 3.11
Classifier: Programming Language :: Python :: 3.12
Requires-Dist: einops (>=0.7.0,<0.8.0)
Requires-Dist: librosa (>=0.10.1,<0.11.0)
Requires-Dist: matplotlib (>=3.7.0,<4.0.0)
Requires-Dist: numpy (>=1.26.2,<2.0.0)
Requires-Dist: pyloudnorm (>=0.1.1,<0.2.0)
Requires-Dist: soundfile (>=0.12.1,<0.13.0)
Requires-Dist: torch (>=2.1.1,<3.0.0) ; sys_platform == "darwin"
Requires-Dist: torch (>=2.1.1,<3.0.0) ; sys_platform == "linux"
Requires-Dist: torch (>=2.1.1,<3.0.0) ; sys_platform == "win32"
Requires-Dist: torch-dct (>=0.1.6,<0.2.0)
